sshanalysis.py
sshanalysis-0.0.2.dist-info/METADATA
sshanalysis-0.0.2.dist-info/WHEEL
sshanalysis-0.0.2.dist-info/entry_points.txt
sshanalysis-0.0.2.dist-info/top_level.txt
sshanalysis-0.0.2.dist-info/RECORD
