Metadata-Version: 2.1
Name: sshanalysis
Version: 0.0.2
Summary: A visualization analysis tool against ssh-server attacks
Home-page: https://github.com/y-takefuji/sshanalysis
Author: yoshiyasu takefuji
Author-email: takefuji@keio.jp
License: UNKNOWN
Project-URL: Bug Tracker, https://github.com/y-takefuji/sshanalysis
Platform: UNKNOWN
Classifier: Programming Language :: Python :: 3
Classifier: License :: OSI Approved :: MIT License
Classifier: Operating System :: OS Independent
Requires-Python: >=3.8
